opensearch_helper/__init__.py
opensearch_helper/bp/__init__.py
opensearch_helper/bp/opensearch_aws.py
opensearch_helper/bp/opensearch_dev.py
opensearch_helper/dmo/__init__.py
opensearch_helper/dmo/aws_client_httpauth.py
opensearch_helper/dmo/aws_client_serverless.py
opensearch_helper/dmo/confidence_compute.py
opensearch_helper/dmo/query_dsl_generator.py
opensearch_helper/dto/__init__.py
opensearch_helper/dto/aws_client_type.py
opensearch_helper/dto/typedefs.py
opensearch_helper/svc/__init__.py
opensearch_helper/svc/query_opensearch.py
opensearch_helper-0.1.28.dist-info/METADATA
opensearch_helper-0.1.28.dist-info/WHEEL
opensearch_helper-0.1.28.dist-info/RECORD
