Metadata-Version: 2.1
Name: opensearch-helper
Version: 0.1.28
Summary: OpenSearch Helper for Easy I/O
Home-page: https://github.com/craigtrim/opensearch-helper
License: None
Keywords: nlp,nlu,opensearch,elasticsearch,aws,search
Author: Craig Trim
Author-email: craigtrim@gmail.com
Maintainer: Craig Trim
Maintainer-email: craigtrim@gmail.com
Requires-Python: >=3.8.5,<4.0.0
Classifier: Development Status :: 4 - Beta
Classifier: License :: Other/Proprietary License
Classifier: Programming Language :: Python :: 3
Classifier: Programming Language :: Python :: 3.9
Classifier: Programming Language :: Python :: 3.10
Classifier: Programming Language :: Python :: 3.11
Classifier: Topic :: Scientific/Engineering :: Artificial Intelligence
Classifier: Topic :: Software Development :: Libraries :: Python Modules
Requires-Dist: baseblock
Requires-Dist: boto3
Requires-Dist: fast-sentence-tokenize
Requires-Dist: nltk (==3.8.1)
Requires-Dist: opensearch-py (>=2.2.0,<3.0.0)
Requires-Dist: requests
Requires-Dist: requests_aws4auth
Project-URL: Bug Tracker, https://github.com/craigtrim/opensearch-helper/issues
Project-URL: Repository, https://github.com/craigtrim/opensearch-helper
